.DS_Store
jarvis_sdk/__init__.py
jarvis_sdk/jarvis_auth.py
jarvis_sdk/jarvis_config.py
jarvis_sdk/jarvis_configuration_manager.py
jarvis_sdk/jarvis_crypto.py
jarvis_sdk/jarvis_gcp_cf_manager.py
jarvis_sdk/jarvis_help.py
jarvis_sdk/jarvis_misc.py
jarvis_sdk/jarvissdk.py
jarvis_sdk/sql_dag_generator.py
jarvis_sdk-1.1.9.dist-info/METADATA
jarvis_sdk-1.1.9.dist-info/WHEEL
jarvis_sdk-1.1.9.dist-info/entry_points.txt
jarvis_sdk-1.1.9.dist-info/top_level.txt
jarvis_sdk-1.1.9.dist-info/RECORD
